{
  "_comment": "This file was generated by Supernova, don't change by hand",
  "spacing0rem": {
    "value": "0rem",
    "type": "dimension"
  },
  "spacing0125rem": {
    "value": "0.1429rem",
    "type": "dimension"
  },
  "spacing025rem": {
    "value": "0.2857rem",
    "type": "dimension"
  },
  "spacing0375rem": {
    "value": "0.4286rem",
    "type": "dimension"
  },
  "spacing05rem": {
    "value": "0.7143rem",
    "type": "dimension"
  },
  "spacing075rem": {
    "value": "1rem",
    "type": "dimension"
  },
  "spacing1rem": {
    "value": "1.2857rem",
    "type": "dimension"
  },
  "spacing125rem": {
    "value": "1.4286rem",
    "type": "dimension"
  },
  "spacing15rem": {
    "value": "1.7143rem",
    "type": "dimension"
  },
  "spacing2rem": {
    "value": "2.2857rem",
    "type": "dimension"
  },
  "spacing25rem": {
    "value": "2.8571rem",
    "type": "dimension"
  },
  "spacing3rem": {
    "value": "3.4286rem",
    "type": "dimension"
  },
  "spacing4rem": {
    "value": "4.5714rem",
    "type": "dimension"
  },
  "spacing5rem": {
    "value": "5.7143rem",
    "type": "dimension"
  },
  "spacing6rem": {
    "value": "6.8571rem",
    "type": "dimension"
  },
  "spacing8rem": {
    "value": "9.1429rem",
    "type": "dimension"
  },
  "radiusXs": {
    "value": "0.1429rem",
    "type": "dimension"
  },
  "radiusSm": {
    "value": "0.2857rem",
    "type": "dimension"
  },
  "radiusMd": {
    "value": "0.4286rem",
    "type": "dimension"
  },
  "radiusLg": {
    "value": "0.5714rem",
    "type": "dimension"
  },
  "radiusXl": {
    "value": "0.8571rem",
    "type": "dimension"
  },
  "radius2xl": {
    "value": "1.1429rem",
    "type": "dimension"
  },
  "radius3xl": {
    "value": "1.4286rem",
    "type": "dimension"
  },
  "radius4xl": {
    "value": "1.7143rem",
    "type": "dimension"
  },
  "radius5xl": {
    "value": "2.5714rem",
    "type": "dimension"
  },
  "radiusFull": {
    "value": "71.3571rem",
    "type": "dimension"
  },
  "fontSizeDisplayDisplay2xl": {
    "value": "6.8571rem",
    "type": "dimension"
  },
  "fontSizeHeadingHeadingXl": {
    "value": "2.8571rem",
    "type": "dimension"
  },
  "fontSizeParagraphParaXl": {
    "value": "1.2857rem",
    "type": "dimension"
  },
  "fontSizeDisplayDisplayXl": {
    "value": "5.1429rem",
    "type": "dimension"
  },
  "fontSizeLabelLabelLg": {
    "value": "1.1429rem",
    "type": "dimension"
  },
  "fontSizeParagraphParaLg": {
    "value": "1.1429rem",
    "type": "dimension"
  },
  "fontSizeParagraphParaMd": {
    "value": "1.0714rem",
    "type": "dimension"
  },
  "fontSizeParagraphParaSm": {
    "value": "0.9286rem",
    "type": "dimension"
  },
  "fontSizeParagraphParaXs": {
    "value": "0.8571rem",
    "type": "dimension"
  },
  "fontSizeParagraphParaXxs": {
    "value": "0.7143rem",
    "type": "dimension"
  },
  "fontSizeLabelLabelMd": {
    "value": "1.0714rem",
    "type": "dimension"
  },
  "fontSizeLabelLabelSm": {
    "value": "0.9286rem",
    "type": "dimension"
  },
  "fontSizeLabelLabelXs": {
    "value": "0.8571rem",
    "type": "dimension"
  },
  "fontSizeHeadingHeadingLg": {
    "value": "2.2857rem",
    "type": "dimension"
  },
  "fontSizeHeadingHeadingMd": {
    "value": "1.7143rem",
    "type": "dimension"
  },
  "fontSizeHeadingHeadingSm": {
    "value": "1.2857rem",
    "type": "dimension"
  },
  "fontSizeDisplayDisplayLg": {
    "value": "4.2857rem",
    "type": "dimension"
  },
  "fontSizeDisplayDisplayMd": {
    "value": "3.4286rem",
    "type": "dimension"
  },
  "fontSizeDisplayDisplaySm": {
    "value": "2.5714rem",
    "type": "dimension"
  },
  "fontSizeDisplayDisplayXs": {
    "value": "1.7143rem",
    "type": "dimension"
  },
  "lineHeightDisplayDisplayXl": {
    "value": "9.4286rem",
    "type": "dimension"
  },
  "lineHeightHeadingHeadingXl": {
    "value": "4rem",
    "type": "dimension"
  },
  "lineHeightLabelLabelLg": {
    "value": "1.7143rem",
    "type": "dimension"
  },
  "lineHeightParagraphParaXl": {
    "value": "2rem",
    "type": "dimension"
  },
  "lineHeightParagraphParaLg": {
    "value": "1.4286rem",
    "type": "dimension"
  },
  "lineHeightParagraphParaMd": {
    "value": "1.4286rem",
    "type": "dimension"
  },
  "lineHeightParagraphParaSm": {
    "value": "1.1429rem",
    "type": "dimension"
  },
  "lineHeightParagraphParaXs": {
    "value": "0.8571rem",
    "type": "dimension"
  },
  "lineHeightParagraphParaXxs": {
    "value": "0.7143rem",
    "type": "dimension"
  },
  "lineHeightLabelLabelMd": {
    "value": "1.4286rem",
    "type": "dimension"
  },
  "lineHeightLabelLabelSm": {
    "value": "1.4286rem",
    "type": "dimension"
  },
  "lineHeightLabelLabelXs": {
    "value": "1.1429rem",
    "type": "dimension"
  },
  "lineHeightHeadingHeadingLg": {
    "value": "3.1429rem",
    "type": "dimension"
  },
  "lineHeightHeadingHeadingMd": {
    "value": "2.5714rem",
    "type": "dimension"
  },
  "lineHeightHeadingHeadingSm": {
    "value": "2rem",
    "type": "dimension"
  },
  "lineHeightDisplayDisplayLg": {
    "value": "7.1429rem",
    "type": "dimension"
  },
  "lineHeightDisplayDisplayMd": {
    "value": "6rem",
    "type": "dimension"
  },
  "lineHeightDisplayDisplaySm": {
    "value": "4.5714rem",
    "type": "dimension"
  },
  "letterSpacingDisplayDisplayXl": {
    "value": "-0.2714rem",
    "type": "dimension"
  },
  "letterSpacingDisplayDisplayLg": {
    "value": "-0.2071rem",
    "type": "dimension"
  },
  "letterSpacingDisplayDisplayMd": {
    "value": "-0.1714rem",
    "type": "dimension"
  },
  "letterSpacingDisplayDisplaySm": {
    "value": "-0.1286rem",
    "type": "dimension"
  },
  "letterSpacingHeadingHeadingXl": {
    "value": "-0.0571rem",
    "type": "dimension"
  },
  "letterSpacingHeadingHeadingLg": {
    "value": "-0.0429rem",
    "type": "dimension"
  },
  "letterSpacingHeadingHeadingMd": {
    "value": "-0.0357rem",
    "type": "dimension"
  },
  "letterSpacingHeadingHeadingSm": {
    "value": "-0.0286rem",
    "type": "dimension"
  },
  "letterSpacingLabelLabelLg": {
    "value": "-0.0286rem",
    "type": "dimension"
  },
  "letterSpacingLabelLabelMd": {
    "value": "-0.0214rem",
    "type": "dimension"
  },
  "letterSpacingLabelLabelSm": {
    "value": "-0.0214rem",
    "type": "dimension"
  },
  "letterSpacingLabelLabelXs": {
    "value": "-0.0143rem",
    "type": "dimension"
  },
  "letterSpacingParagraphParaXl": {
    "value": "-0.0286rem",
    "type": "dimension"
  },
  "letterSpacingParagraphParaLg": {
    "value": "-0.0214rem",
    "type": "dimension"
  },
  "letterSpacingParagraphParaMd": {
    "value": "-0.0214rem",
    "type": "dimension"
  },
  "letterSpacingParagraphParaSm": {
    "value": "-0.0143rem",
    "type": "dimension"
  },
  "letterSpacingParagraphParaXs": {
    "value": "-0.0143rem",
    "type": "dimension"
  }
}